odoo/addons/date_range/README.rst
odoo/addons/date_range/__init__.py
odoo/addons/date_range/__manifest__.py
odoo/addons/date_range/i18n/.empty
odoo/addons/date_range/i18n/am.po
odoo/addons/date_range/i18n/ar.po
odoo/addons/date_range/i18n/bg.po
odoo/addons/date_range/i18n/bs.po
odoo/addons/date_range/i18n/ca.po
odoo/addons/date_range/i18n/ca_ES.po
odoo/addons/date_range/i18n/cs.po
odoo/addons/date_range/i18n/da.po
odoo/addons/date_range/i18n/date_range.pot
odoo/addons/date_range/i18n/de.po
odoo/addons/date_range/i18n/el_GR.po
odoo/addons/date_range/i18n/en_AU.po
odoo/addons/date_range/i18n/en_GB.po
odoo/addons/date_range/i18n/es.po
odoo/addons/date_range/i18n/es_AR.po
odoo/addons/date_range/i18n/es_CL.po
odoo/addons/date_range/i18n/es_CO.po
odoo/addons/date_range/i18n/es_CR.po
odoo/addons/date_range/i18n/es_DO.po
odoo/addons/date_range/i18n/es_EC.po
odoo/addons/date_range/i18n/es_ES.po
odoo/addons/date_range/i18n/es_MX.po
odoo/addons/date_range/i18n/es_PE.po
odoo/addons/date_range/i18n/es_PY.po
odoo/addons/date_range/i18n/es_VE.po
odoo/addons/date_range/i18n/et.po
odoo/addons/date_range/i18n/eu.po
odoo/addons/date_range/i18n/fa.po
odoo/addons/date_range/i18n/fi.po
odoo/addons/date_range/i18n/fr.po
odoo/addons/date_range/i18n/fr_CA.po
odoo/addons/date_range/i18n/fr_CH.po
odoo/addons/date_range/i18n/fr_FR.po
odoo/addons/date_range/i18n/gl.po
odoo/addons/date_range/i18n/gl_ES.po
odoo/addons/date_range/i18n/he.po
odoo/addons/date_range/i18n/hi.po
odoo/addons/date_range/i18n/hr.po
odoo/addons/date_range/i18n/hr_HR.po
odoo/addons/date_range/i18n/hu.po
odoo/addons/date_range/i18n/id.po
odoo/addons/date_range/i18n/it.po
odoo/addons/date_range/i18n/ja.po
odoo/addons/date_range/i18n/ko.po
odoo/addons/date_range/i18n/lo.po
odoo/addons/date_range/i18n/lt.po
odoo/addons/date_range/i18n/lt_LT.po
odoo/addons/date_range/i18n/lv.po
odoo/addons/date_range/i18n/mk.po
odoo/addons/date_range/i18n/mn.po
odoo/addons/date_range/i18n/nb.po
odoo/addons/date_range/i18n/nb_NO.po
odoo13_addon_date_range-13.0.1.0.2.dist-info/METADATA
odoo13_addon_date_range-13.0.1.0.2.dist-info/WHEEL
odoo13_addon_date_range-13.0.1.0.2.dist-info/top_level.txt
odoo13_addon_date_range-13.0.1.0.2.dist-info/RECORD
