Metadata-Version: 2.1
Name: odoo13-addon-date-range
Version: 13.0.1.0.2
Summary: Manage all kind of date range
Home-page: https://github.com/oca/server-ux
Author: ACSONE SA/NV, Odoo Community Association (OCA)
Author-email: support@odoo-community.org
License: AGPL-3
Platform: UNKNOWN
Classifier: Programming Language :: Python
Classifier: Framework :: Odoo
Classifier: License :: OSI Approved :: GNU Affero General Public License v3
Classifier: Development Status :: 6 - Mature
Requires-Python: >=3.5
Requires-Dist: odoo (<13.1dev,>=13.0a)
